mcv
