Metadata-Version: 1.0
Name: mcv
Version: 0.31.2
Summary: Spartan configuration management in Python
Home-page: https://github.com/framed-data/mcv
Author: Elliot Block
Author-email: elliot@framed.io
License: UNKNOWN
Platform: UNKNOWN
